<?xml version="1.0"?>
<!DOCTYPE hibernate-mapping PUBLIC "-//Hibernate/Hibernate Mapping DTD 3.0//EN"
"http://hibernate.sourceforge.net/hibernate-mapping-3.0.dtd">
<!-- 
	Mapping file autogenerated by MyEclipse - Hibernate Tools
-->
<hibernate-mapping>
	<class name="com.whaty.platform.entity.bean.WeVoteResult"
		table="WE_VOTE_RESULTS">
		<!-- 主键 -->
		<id name="wvrId" type="java.lang.String">
			<column name="WVR_ID" length="50" />
			<generator class="uuid" />
		</id>
		<!-- 昵称 -->
		<property name="wvrNickname" type="java.lang.String">
			<column name="WVR_NICKNAME" />
		</property>
		<!-- 回答（当非选择题） -->
		<property name="wvrAnswer" type="java.lang.String">
			<column name="WVR_ANSWER" />
		</property>
		<!-- 用户ID -->
		<property name="wvrUid" type="java.lang.String">
			<column name="WVR_UID" />
		</property>
		<!-- 问题值ID -->
		<property name="wvrWvoId" type="java.lang.String">
			<column name="WVR_WVO_ID" />
		</property>
	</class>
</hibernate-mapping>
